summarize_template/__init__.py
summarize_template/cli.py
summarize_template-0.1.dist-info/LICENSE
summarize_template-0.1.dist-info/METADATA
summarize_template-0.1.dist-info/WHEEL
summarize_template-0.1.dist-info/entry_points.txt
summarize_template-0.1.dist-info/top_level.txt
summarize_template-0.1.dist-info/RECORD
