Metadata-Version: 2.1
Name: summarize-template
Version: 0.1
Summary: Show a summary of a Django or Jinja template
Home-page: https://github.com/simonw/summarize-template
Author: Simon Willison
License: Apache License, Version 2.0
Project-URL: Issues, https://github.com/simonw/summarize-template/issues
Project-URL: CI, https://github.com/simonw/summarize-template/actions
Project-URL: Changelog, https://github.com/simonw/summarize-template/releases
Platform: UNKNOWN
Requires-Python: >=3.7
License-File: LICENSE
Requires-Dist: click
Provides-Extra: test
Requires-Dist: pytest ; extra == 'test'
